cdek/__init__.py
cdek/__version__.py
cdek/api.py
cdek/entities.py
cdek/utils.py
fs_cdek_api-1.4.1.dist-info/LICENSE
fs_cdek_api-1.4.1.dist-info/METADATA
fs_cdek_api-1.4.1.dist-info/WHEEL
fs_cdek_api-1.4.1.dist-info/top_level.txt
fs_cdek_api-1.4.1.dist-info/RECORD
