Metadata-Version: 2.1
Name: fs-cdek-api
Version: 1.4.1
Summary: CDEK API wrapper
Home-page: https://github.com/fogstream/fs-cdek-api
Maintainer: fadedDexofan
Maintainer-email: fadeddexofan@gmail.com
License: MIT
Keywords: cdek,api,cdek,fs-cdek-api,sdk,integration,fogstream
Platform: UNKNOWN
Classifier: License :: OSI Approved :: MIT License
Classifier: Development Status :: 5 - Production/Stable
Classifier: Intended Audience :: Developers
Classifier: Operating System :: Unix
Classifier: Topic :: Software Development :: Libraries
Classifier: Programming Language :: Python :: 3
Classifier: Programming Language :: Python :: 3.6
Classifier: Programming Language :: Python :: 3.7
Classifier: Programming Language :: Python :: Implementation :: CPython
Requires-Python: >=3.6.0
Requires-Dist: requests (<3,>=2.22.0)
Requires-Dist: boltons (<20,>=19.1.0)
Provides-Extra: for_tests
Requires-Dist: pytest (<5.1,>=5.0) ; extra == 'for_tests'
Requires-Dist: pytest-cov (<=3) ; extra == 'for_tests'
Requires-Dist: pytest-xdist (<2,>=1.29.0) ; extra == 'for_tests'
